csaf/__init__.py
csaf/analyser.py
csaf/cli.py
csaf/config.py
csaf/generator.py
csaf/parser.py
csaf/version.py
csaf_tool-0.3.1.dist-info/LICENSE
csaf_tool-0.3.1.dist-info/METADATA
csaf_tool-0.3.1.dist-info/WHEEL
csaf_tool-0.3.1.dist-info/entry_points.txt
csaf_tool-0.3.1.dist-info/top_level.txt
csaf_tool-0.3.1.dist-info/RECORD
