Metadata-Version: 2.1
Name: csaf-tool
Version: 0.3.1
Summary: CSAF generator and analyser
Home-page: https://github.com/anthonyharrison/csaf
Author: Anthony Harrison
Author-email: anthony.p.harrison@gmail.com
Maintainer: Anthony Harrison
Maintainer-email: anthony.p.harrison@gmail.com
License: MIT
Keywords: security,tools,CSAF,CSAF 2.0,VexDevSecOps,vulnerabilities
Classifier: Development Status :: 3 - Alpha
Classifier: Intended Audience :: Developers
Classifier: License :: OSI Approved :: MIT License
Classifier: Natural Language :: English
Classifier: Operating System :: OS Independent
Classifier: Programming Language :: Python :: 3.7
Classifier: Programming Language :: Python :: 3.8
Classifier: Programming Language :: Python :: 3.9
Classifier: Programming Language :: Python :: 3.10
Classifier: Programming Language :: Python :: 3.11
Classifier: Programming Language :: Python :: Implementation :: CPython
Classifier: Programming Language :: Python :: Implementation :: PyPy
Requires-Python: >=3.7
License-File: LICENSE
Requires-Dist: packageurl-python
Requires-Dist: rich
